<!-- Copyright 2004 Sun Microsystems, Inc. All Rights Reserved. Redistribution 
	and use in source and binary forms, with or without modification, are permitted 
	provided that the following conditions are met: 1. Redistribution of source 
	code must retain the above copyright notice, this list of conditions and 
	the following disclaimer. 2. Redistribution in binary form must reproduce 
	the above copyright notice, this list of conditions and the following disclaimer 
	in the documentation and/or other materials provided with the distribution. 
	Neither the name of Sun Microsystems, Inc. or the names of contributors may 
	be used to endorse or promote products derived from this software without 
	specific prior written permission. This software is provided "AS IS," without 
	a warranty of any kind. ALL EXPRESS OR IMPLIED CONDITIONS, REPRESENTATIONS 
	AND WARRANTIES, INCLUDING ANY IMPLIED WARRANTY OF MERCHANTABILITY, FITNESS 
	FOR A PARTICULAR PURPOSE OR NON-INFRINGEMENT, ARE HEREBY EXCLUDED. SUN MICROSYSTEMS, 
	INC. ("SUN") AND ITS LICENSORS SHALL NOT BE LIABLE FOR ANY DAMAGES SUFFERED 
	BY LICENSEE AS A RESULT OF USING, MODIFYING OR DISTRIBUTING THIS SOFTWARE 
	OR ITS DERIVATIVES. IN NO EVENT WILL SUN OR ITS LICENSORS BE LIABLE FOR ANY 
	LOST REVENUE, PROFIT OR DATA, OR FOR DIRECT, INDIRECT, SPECIAL, CONSEQUENTIAL, 
	INCIDENTAL OR PUNITIVE DAMAGES, HOWEVER CAUSED AND REGARDLESS OF THE THEORY 
	OF LIABILITY, ARISING OUT OF THE USE OF OR INABILITY TO USE THIS SOFTWARE, 
	EVEN IF SUN HAS BEEN ADVISED OF THE POSSIBILITY OF SUCH DAMAGES. You acknowledge 
	that this software is not designed or intended for use in the design, construction, 
	operation or maintenance of any nuclear facility. -->

<test name="MTAS">

    <policySetReference ref="urn:mtas:RPS:i0000">RPSi0000.xml</policySetReference>
    <policySetReference ref="urn:mtas:PPS:i0000:manager">PPSi0000.xml</policySetReference>
    <policySetReference ref="urn:mtas:PPS:i0000:employee">PPSi0000.xml</policySetReference>
    <policySetReference ref="urn:mtas:RPS:i0000:employee">RPSi0000.xml</policySetReference>
    
    <policySetReference ref="urn:mtas:RPS:i0001">RPSi0001.xml</policySetReference>
    <policySetReference ref="urn:mtas:PPS:i0001:manager">PPSi0001.xml</policySetReference>
    <policySetReference ref="urn:mtas:PPS:i0001:employee">PPSi0001.xml</policySetReference>
    <policySetReference ref="urn:mtas:RPS:i0001:employee">RPSi0001.xml</policySetReference>
    
    <policySetReference ref="urn:mtas:RPS:i0002">RPSi0002.xml</policySetReference>
    <policySetReference ref="urn:mtas:PPS:i0002:manager">PPSi0002.xml</policySetReference>
    <policySetReference ref="urn:mtas:PPS:i0002:employee">PPSi0002.xml</policySetReference>
    <policySetReference ref="urn:mtas:RPS:i0002:employee">RPSi0002.xml</policySetReference>
    
    <policySetReference ref="urn:mtas:RPS:i0003">RPSi0003.xml</policySetReference>
    <policySetReference ref="urn:mtas:PPS:i0003:manager">PPSi0003.xml</policySetReference>
    <policySetReference ref="urn:mtas:PPS:i0003:employee">PPSi0003.xml</policySetReference>
    <policySetReference ref="urn:mtas:RPS:i0003:employee">RPSi0003.xml</policySetReference>
    
    <policySetReference ref="urn:mtas:RPS:i0004">RPSi0004.xml</policySetReference>
    <policySetReference ref="urn:mtas:PPS:i0004:manager">PPSi0004.xml</policySetReference>
    <policySetReference ref="urn:mtas:PPS:i0004:employee">PPSi0004.xml</policySetReference>
    <policySetReference ref="urn:mtas:RPS:i0004:employee">RPSi0004.xml</policySetReference>
    
    <policySetReference ref="urn:mtas:RPS:i0005">RPSi0005.xml</policySetReference>
    <policySetReference ref="urn:mtas:PPS:i0005:manager">PPSi0005.xml</policySetReference>
    <policySetReference ref="urn:mtas:PPS:i0005:employee">PPSi0005.xml</policySetReference>
    <policySetReference ref="urn:mtas:RPS:i0005:employee">RPSi0005.xml</policySetReference>
    
    <policySetReference ref="urn:mtas:RPS:i0006">RPSi0006.xml</policySetReference>
    <policySetReference ref="urn:mtas:PPS:i0006:manager">PPSi0006.xml</policySetReference>
    <policySetReference ref="urn:mtas:PPS:i0006:employee">PPSi0006.xml</policySetReference>
    <policySetReference ref="urn:mtas:RPS:i0006:employee">RPSi0006.xml</policySetReference>
    
    <policySetReference ref="urn:mtas:RPS:i0007">RPSi0007.xml</policySetReference>
    <policySetReference ref="urn:mtas:PPS:i0007:manager">PPSi0007.xml</policySetReference>
    <policySetReference ref="urn:mtas:PPS:i0007:employee">PPSi0007.xml</policySetReference>
    <policySetReference ref="urn:mtas:RPS:i0007:employee">RPSi0007.xml</policySetReference>
    
    <policySetReference ref="urn:mtas:RPS:i0008">RPSi0008.xml</policySetReference>
    <policySetReference ref="urn:mtas:PPS:i0008:manager">PPSi0008.xml</policySetReference>
    <policySetReference ref="urn:mtas:PPS:i0008:employee">PPSi0008.xml</policySetReference>
    <policySetReference ref="urn:mtas:RPS:i0008:employee">RPSi0008.xml</policySetReference>
    
    <policySetReference ref="urn:mtas:RPS:i0009">RPSi0009.xml</policySetReference>
    <policySetReference ref="urn:mtas:PPS:i0009:manager">PPSi0009.xml</policySetReference>
    <policySetReference ref="urn:mtas:PPS:i0009:employee">PPSi0009.xml</policySetReference>
    <policySetReference ref="urn:mtas:RPS:i0009:employee">RPSi0009.xml</policySetReference>
    
    <policySetReference ref="urn:mtas:RPS:i0010">RPSi0010.xml</policySetReference>
    <policySetReference ref="urn:mtas:PPS:i0010:manager">PPSi0010.xml</policySetReference>
    <policySetReference ref="urn:mtas:PPS:i0010:employee">PPSi0010.xml</policySetReference>
    <policySetReference ref="urn:mtas:RPS:i0010:employee">RPSi0010.xml</policySetReference>
    
    <policySetReference ref="urn:mtas:RPS:i0011">RPSi0011.xml</policySetReference>
    <policySetReference ref="urn:mtas:PPS:i0011:manager">PPSi0011.xml</policySetReference>
    <policySetReference ref="urn:mtas:PPS:i0011:employee">PPSi0011.xml</policySetReference>
    <policySetReference ref="urn:mtas:RPS:i0011:employee">RPSi0011.xml</policySetReference>
    
    <policySetReference ref="urn:mtas:RPS:i0012">RPSi0012.xml</policySetReference>
    <policySetReference ref="urn:mtas:PPS:i0012:manager">PPSi0012.xml</policySetReference>
    <policySetReference ref="urn:mtas:PPS:i0012:employee">PPSi0012.xml</policySetReference>
    <policySetReference ref="urn:mtas:RPS:i0012:employee">RPSi0012.xml</policySetReference>
    
    <policySetReference ref="urn:mtas:RPS:i0013">RPSi0013.xml</policySetReference>
    <policySetReference ref="urn:mtas:PPS:i0013:manager">PPSi0013.xml</policySetReference>
    <policySetReference ref="urn:mtas:PPS:i0013:employee">PPSi0013.xml</policySetReference>
    <policySetReference ref="urn:mtas:RPS:i0013:employee">RPSi0013.xml</policySetReference>
    
    <policySetReference ref="urn:mtas:RPS:i0014">RPSi0014.xml</policySetReference>
    <policySetReference ref="urn:mtas:PPS:i0014:manager">PPSi0014.xml</policySetReference>
    <policySetReference ref="urn:mtas:PPS:i0014:employee">PPSi0014.xml</policySetReference>
    <policySetReference ref="urn:mtas:RPS:i0014:employee">RPSi0014.xml</policySetReference>
    
    <policySetReference ref="urn:mtas:RPS:i0015">RPSi0015.xml</policySetReference>
    <policySetReference ref="urn:mtas:PPS:i0015:manager">PPSi0015.xml</policySetReference>
    <policySetReference ref="urn:mtas:PPS:i0015:employee">PPSi0015.xml</policySetReference>
    <policySetReference ref="urn:mtas:RPS:i0015:employee">RPSi0015.xml</policySetReference>
    
    <policySetReference ref="urn:mtas:RPS:i0016">RPSi0016.xml</policySetReference>
    <policySetReference ref="urn:mtas:PPS:i0016:manager">PPSi0016.xml</policySetReference>
    <policySetReference ref="urn:mtas:PPS:i0016:employee">PPSi0016.xml</policySetReference>
    <policySetReference ref="urn:mtas:RPS:i0016:employee">RPSi0016.xml</policySetReference>
    
    <policySetReference ref="urn:mtas:RPS:i0017">RPSi0017.xml</policySetReference>
    <policySetReference ref="urn:mtas:PPS:i0017:manager">PPSi0017.xml</policySetReference>
    <policySetReference ref="urn:mtas:PPS:i0017:employee">PPSi0017.xml</policySetReference>
    <policySetReference ref="urn:mtas:RPS:i0017:employee">RPSi0017.xml</policySetReference>
    
    <policySetReference ref="urn:mtas:RPS:i0018">RPSi0018.xml</policySetReference>
    <policySetReference ref="urn:mtas:PPS:i0018:manager">PPSi0018.xml</policySetReference>
    <policySetReference ref="urn:mtas:PPS:i0018:employee">PPSi0018.xml</policySetReference>
    <policySetReference ref="urn:mtas:RPS:i0018:employee">RPSi0018.xml</policySetReference>
    
    <policySetReference ref="urn:mtas:RPS:i0019">RPSi0019.xml</policySetReference>
    <policySetReference ref="urn:mtas:PPS:i0019:manager">PPSi0019.xml</policySetReference>
    <policySetReference ref="urn:mtas:PPS:i0019:employee">PPSi0019.xml</policySetReference>
    <policySetReference ref="urn:mtas:RPS:i0019:employee">RPSi0019.xml</policySetReference>
    
    <policySetReference ref="urn:mtas:RPS:i0020">RPSi0020.xml</policySetReference>
    <policySetReference ref="urn:mtas:PPS:i0020:manager">PPSi0020.xml</policySetReference>
    <policySetReference ref="urn:mtas:PPS:i0020:employee">PPSi0020.xml</policySetReference>
    <policySetReference ref="urn:mtas:RPS:i0020:employee">RPSi0020.xml</policySetReference>
    
    <policySetReference ref="urn:mtas:RPS:i0021">RPSi0021.xml</policySetReference>
    <policySetReference ref="urn:mtas:PPS:i0021:manager">PPSi0021.xml</policySetReference>
    <policySetReference ref="urn:mtas:PPS:i0021:employee">PPSi0021.xml</policySetReference>
    <policySetReference ref="urn:mtas:RPS:i0021:employee">RPSi0021.xml</policySetReference>
    
    <policySetReference ref="urn:mtas:RPS:i0022">RPSi0022.xml</policySetReference>
    <policySetReference ref="urn:mtas:PPS:i0022:manager">PPSi0022.xml</policySetReference>
    <policySetReference ref="urn:mtas:PPS:i0022:employee">PPSi0022.xml</policySetReference>
    <policySetReference ref="urn:mtas:RPS:i0022:employee">RPSi0022.xml</policySetReference>
    
    <policySetReference ref="urn:mtas:RPS:i0023">RPSi0023.xml</policySetReference>
    <policySetReference ref="urn:mtas:PPS:i0023:manager">PPSi0023.xml</policySetReference>
    <policySetReference ref="urn:mtas:PPS:i0023:employee">PPSi0023.xml</policySetReference>
    <policySetReference ref="urn:mtas:RPS:i0023:employee">RPSi0023.xml</policySetReference>
    
    <policySetReference ref="urn:mtas:RPS:i0024">RPSi0024.xml</policySetReference>
    <policySetReference ref="urn:mtas:PPS:i0024:manager">PPSi0024.xml</policySetReference>
    <policySetReference ref="urn:mtas:PPS:i0024:employee">PPSi0024.xml</policySetReference>
    <policySetReference ref="urn:mtas:RPS:i0024:employee">RPSi0024.xml</policySetReference>
    
    <policySetReference ref="urn:mtas:RPS:i0025">RPSi0025.xml</policySetReference>
    <policySetReference ref="urn:mtas:PPS:i0025:manager">PPSi0025.xml</policySetReference>
    <policySetReference ref="urn:mtas:PPS:i0025:employee">PPSi0025.xml</policySetReference>
    <policySetReference ref="urn:mtas:RPS:i0025:employee">RPSi0025.xml</policySetReference>
    
    <policySetReference ref="urn:mtas:RPS:i0026">RPSi0026.xml</policySetReference>
    <policySetReference ref="urn:mtas:PPS:i0026:manager">PPSi0026.xml</policySetReference>
    <policySetReference ref="urn:mtas:PPS:i0026:employee">PPSi0026.xml</policySetReference>
    <policySetReference ref="urn:mtas:RPS:i0026:employee">RPSi0026.xml</policySetReference>
    
    <policySetReference ref="urn:mtas:RPS:i0027">RPSi0027.xml</policySetReference>
    <policySetReference ref="urn:mtas:PPS:i0027:manager">PPSi0027.xml</policySetReference>
    <policySetReference ref="urn:mtas:PPS:i0027:employee">PPSi0027.xml</policySetReference>
    <policySetReference ref="urn:mtas:RPS:i0027:employee">RPSi0027.xml</policySetReference>
    
    <policySetReference ref="urn:mtas:RPS:i0028">RPSi0028.xml</policySetReference>
    <policySetReference ref="urn:mtas:PPS:i0028:manager">PPSi0028.xml</policySetReference>
    <policySetReference ref="urn:mtas:PPS:i0028:employee">PPSi0028.xml</policySetReference>
    <policySetReference ref="urn:mtas:RPS:i0028:employee">RPSi0028.xml</policySetReference>
    
    <policySetReference ref="urn:mtas:RPS:i0029">RPSi0029.xml</policySetReference>
    <policySetReference ref="urn:mtas:PPS:i0029:manager">PPSi0029.xml</policySetReference>
    <policySetReference ref="urn:mtas:PPS:i0029:employee">PPSi0029.xml</policySetReference>
    <policySetReference ref="urn:mtas:RPS:i0029:employee">RPSi0029.xml</policySetReference>
    
    <policySetReference ref="urn:mtas:RPS:i0030">RPSi0030.xml</policySetReference>
    <policySetReference ref="urn:mtas:PPS:i0030:manager">PPSi0030.xml</policySetReference>
    <policySetReference ref="urn:mtas:PPS:i0030:employee">PPSi0030.xml</policySetReference>
    <policySetReference ref="urn:mtas:RPS:i0030:employee">RPSi0030.xml</policySetReference>
    
    <policySetReference ref="urn:mtas:RPS:i0031">RPSi0031.xml</policySetReference>
    <policySetReference ref="urn:mtas:PPS:i0031:manager">PPSi0031.xml</policySetReference>
    <policySetReference ref="urn:mtas:PPS:i0031:employee">PPSi0031.xml</policySetReference>
    <policySetReference ref="urn:mtas:RPS:i0031:employee">RPSi0031.xml</policySetReference>
    
    <policySetReference ref="urn:mtas:RPS:i0032">RPSi0032.xml</policySetReference>
    <policySetReference ref="urn:mtas:PPS:i0032:manager">PPSi0032.xml</policySetReference>
    <policySetReference ref="urn:mtas:PPS:i0032:employee">PPSi0032.xml</policySetReference>
    <policySetReference ref="urn:mtas:RPS:i0032:employee">RPSi0032.xml</policySetReference>
    
    <policySetReference ref="urn:mtas:RPS:i0033">RPSi0033.xml</policySetReference>
    <policySetReference ref="urn:mtas:PPS:i0033:manager">PPSi0033.xml</policySetReference>
    <policySetReference ref="urn:mtas:PPS:i0033:employee">PPSi0033.xml</policySetReference>
    <policySetReference ref="urn:mtas:RPS:i0033:employee">RPSi0033.xml</policySetReference>
    
    <policySetReference ref="urn:mtas:RPS:i0034">RPSi0034.xml</policySetReference>
    <policySetReference ref="urn:mtas:PPS:i0034:manager">PPSi0034.xml</policySetReference>
    <policySetReference ref="urn:mtas:PPS:i0034:employee">PPSi0034.xml</policySetReference>
    <policySetReference ref="urn:mtas:RPS:i0034:employee">RPSi0034.xml</policySetReference>
    
    <policySetReference ref="urn:mtas:RPS:i0035">RPSi0035.xml</policySetReference>
    <policySetReference ref="urn:mtas:PPS:i0035:manager">PPSi0035.xml</policySetReference>
    <policySetReference ref="urn:mtas:PPS:i0035:employee">PPSi0035.xml</policySetReference>
    <policySetReference ref="urn:mtas:RPS:i0035:employee">RPSi0035.xml</policySetReference>
    
    <policySetReference ref="urn:mtas:RPS:i0036">RPSi0036.xml</policySetReference>
    <policySetReference ref="urn:mtas:PPS:i0036:manager">PPSi0036.xml</policySetReference>
    <policySetReference ref="urn:mtas:PPS:i0036:employee">PPSi0036.xml</policySetReference>
    <policySetReference ref="urn:mtas:RPS:i0036:employee">RPSi0036.xml</policySetReference>
    
    <policySetReference ref="urn:mtas:RPS:i0037">RPSi0037.xml</policySetReference>
    <policySetReference ref="urn:mtas:PPS:i0037:manager">PPSi0037.xml</policySetReference>
    <policySetReference ref="urn:mtas:PPS:i0037:employee">PPSi0037.xml</policySetReference>
    <policySetReference ref="urn:mtas:RPS:i0037:employee">RPSi0037.xml</policySetReference>
    
    <policySetReference ref="urn:mtas:RPS:i0038">RPSi0038.xml</policySetReference>
    <policySetReference ref="urn:mtas:PPS:i0038:manager">PPSi0038.xml</policySetReference>
    <policySetReference ref="urn:mtas:PPS:i0038:employee">PPSi0038.xml</policySetReference>
    <policySetReference ref="urn:mtas:RPS:i0038:employee">RPSi0038.xml</policySetReference>
    
    <policySetReference ref="urn:mtas:RPS:i0039">RPSi0039.xml</policySetReference>
    <policySetReference ref="urn:mtas:PPS:i0039:manager">PPSi0039.xml</policySetReference>
    <policySetReference ref="urn:mtas:PPS:i0039:employee">PPSi0039.xml</policySetReference>
    <policySetReference ref="urn:mtas:RPS:i0039:employee">RPSi0039.xml</policySetReference>
    
    <policySetReference ref="urn:mtas:RPS:i0040">RPSi0040.xml</policySetReference>
    <policySetReference ref="urn:mtas:PPS:i0040:manager">PPSi0040.xml</policySetReference>
    <policySetReference ref="urn:mtas:PPS:i0040:employee">PPSi0040.xml</policySetReference>
    <policySetReference ref="urn:mtas:RPS:i0040:employee">RPSi0040.xml</policySetReference>
    
    <policySetReference ref="urn:mtas:RPS:i0041">RPSi0041.xml</policySetReference>
    <policySetReference ref="urn:mtas:PPS:i0041:manager">PPSi0041.xml</policySetReference>
    <policySetReference ref="urn:mtas:PPS:i0041:employee">PPSi0041.xml</policySetReference>
    <policySetReference ref="urn:mtas:RPS:i0041:employee">RPSi0041.xml</policySetReference>
    
    <policySetReference ref="urn:mtas:RPS:i0042">RPSi0042.xml</policySetReference>
    <policySetReference ref="urn:mtas:PPS:i0042:manager">PPSi0042.xml</policySetReference>
    <policySetReference ref="urn:mtas:PPS:i0042:employee">PPSi0042.xml</policySetReference>
    <policySetReference ref="urn:mtas:RPS:i0042:employee">RPSi0042.xml</policySetReference>
    
    <policySetReference ref="urn:mtas:RPS:i0043">RPSi0043.xml</policySetReference>
    <policySetReference ref="urn:mtas:PPS:i0043:manager">PPSi0043.xml</policySetReference>
    <policySetReference ref="urn:mtas:PPS:i0043:employee">PPSi0043.xml</policySetReference>
    <policySetReference ref="urn:mtas:RPS:i0043:employee">RPSi0043.xml</policySetReference>
    
    <policySetReference ref="urn:mtas:RPS:i0044">RPSi0044.xml</policySetReference>
    <policySetReference ref="urn:mtas:PPS:i0044:manager">PPSi0044.xml</policySetReference>
    <policySetReference ref="urn:mtas:PPS:i0044:employee">PPSi0044.xml</policySetReference>
    <policySetReference ref="urn:mtas:RPS:i0044:employee">RPSi0044.xml</policySetReference>
    
    <policySetReference ref="urn:mtas:RPS:i0045">RPSi0045.xml</policySetReference>
    <policySetReference ref="urn:mtas:PPS:i0045:manager">PPSi0045.xml</policySetReference>
    <policySetReference ref="urn:mtas:PPS:i0045:employee">PPSi0045.xml</policySetReference>
    <policySetReference ref="urn:mtas:RPS:i0045:employee">RPSi0045.xml</policySetReference>
    
    <policySetReference ref="urn:mtas:RPS:i0046">RPSi0046.xml</policySetReference>
    <policySetReference ref="urn:mtas:PPS:i0046:manager">PPSi0046.xml</policySetReference>
    <policySetReference ref="urn:mtas:PPS:i0046:employee">PPSi0046.xml</policySetReference>
    <policySetReference ref="urn:mtas:RPS:i0046:employee">RPSi0046.xml</policySetReference>
    
    <policySetReference ref="urn:mtas:RPS:i0047">RPSi0047.xml</policySetReference>
    <policySetReference ref="urn:mtas:PPS:i0047:manager">PPSi0047.xml</policySetReference>
    <policySetReference ref="urn:mtas:PPS:i0047:employee">PPSi0047.xml</policySetReference>
    <policySetReference ref="urn:mtas:RPS:i0047:employee">RPSi0047.xml</policySetReference>
    
    <policySetReference ref="urn:mtas:RPS:i0048">RPSi0048.xml</policySetReference>
    <policySetReference ref="urn:mtas:PPS:i0048:manager">PPSi0048.xml</policySetReference>
    <policySetReference ref="urn:mtas:PPS:i0048:employee">PPSi0048.xml</policySetReference>
    <policySetReference ref="urn:mtas:RPS:i0048:employee">RPSi0048.xml</policySetReference>
    
    <policySetReference ref="urn:mtas:RPS:i0049">RPSi0049.xml</policySetReference>
    <policySetReference ref="urn:mtas:PPS:i0049:manager">PPSi0049.xml</policySetReference>
    <policySetReference ref="urn:mtas:PPS:i0049:employee">PPSi0049.xml</policySetReference>
    <policySetReference ref="urn:mtas:RPS:i0049:employee">RPSi0049.xml</policySetReference>
    
    <policySetReference ref="urn:mtas:RPS:i0050">RPSi0050.xml</policySetReference>
    <policySetReference ref="urn:mtas:PPS:i0050:manager">PPSi0050.xml</policySetReference>
    <policySetReference ref="urn:mtas:PPS:i0050:employee">PPSi0050.xml</policySetReference>
    <policySetReference ref="urn:mtas:RPS:i0050:employee">RPSi0050.xml</policySetReference>
    
    <policySetReference ref="urn:mtas:RPS:i0051">RPSi0051.xml</policySetReference>
    <policySetReference ref="urn:mtas:PPS:i0051:manager">PPSi0051.xml</policySetReference>
    <policySetReference ref="urn:mtas:PPS:i0051:employee">PPSi0051.xml</policySetReference>
    <policySetReference ref="urn:mtas:RPS:i0051:employee">RPSi0051.xml</policySetReference>
    
    <policySetReference ref="urn:mtas:RPS:i0052">RPSi0052.xml</policySetReference>
    <policySetReference ref="urn:mtas:PPS:i0052:manager">PPSi0052.xml</policySetReference>
    <policySetReference ref="urn:mtas:PPS:i0052:employee">PPSi0052.xml</policySetReference>
    <policySetReference ref="urn:mtas:RPS:i0052:employee">RPSi0052.xml</policySetReference>
    
    <policySetReference ref="urn:mtas:RPS:i0053">RPSi0053.xml</policySetReference>
    <policySetReference ref="urn:mtas:PPS:i0053:manager">PPSi0053.xml</policySetReference>
    <policySetReference ref="urn:mtas:PPS:i0053:employee">PPSi0053.xml</policySetReference>
    <policySetReference ref="urn:mtas:RPS:i0053:employee">RPSi0053.xml</policySetReference>
    
    <policySetReference ref="urn:mtas:RPS:i0054">RPSi0054.xml</policySetReference>
    <policySetReference ref="urn:mtas:PPS:i0054:manager">PPSi0054.xml</policySetReference>
    <policySetReference ref="urn:mtas:PPS:i0054:employee">PPSi0054.xml</policySetReference>
    <policySetReference ref="urn:mtas:RPS:i0054:employee">RPSi0054.xml</policySetReference>
    
    <policySetReference ref="urn:mtas:RPS:i0055">RPSi0055.xml</policySetReference>
    <policySetReference ref="urn:mtas:PPS:i0055:manager">PPSi0055.xml</policySetReference>
    <policySetReference ref="urn:mtas:PPS:i0055:employee">PPSi0055.xml</policySetReference>
    <policySetReference ref="urn:mtas:RPS:i0055:employee">RPSi0055.xml</policySetReference>
    
    <policySetReference ref="urn:mtas:RPS:i0056">RPSi0056.xml</policySetReference>
    <policySetReference ref="urn:mtas:PPS:i0056:manager">PPSi0056.xml</policySetReference>
    <policySetReference ref="urn:mtas:PPS:i0056:employee">PPSi0056.xml</policySetReference>
    <policySetReference ref="urn:mtas:RPS:i0056:employee">RPSi0056.xml</policySetReference>
    
    <policySetReference ref="urn:mtas:RPS:i0057">RPSi0057.xml</policySetReference>
    <policySetReference ref="urn:mtas:PPS:i0057:manager">PPSi0057.xml</policySetReference>
    <policySetReference ref="urn:mtas:PPS:i0057:employee">PPSi0057.xml</policySetReference>
    <policySetReference ref="urn:mtas:RPS:i0057:employee">RPSi0057.xml</policySetReference>
    
    <policySetReference ref="urn:mtas:RPS:i0058">RPSi0058.xml</policySetReference>
    <policySetReference ref="urn:mtas:PPS:i0058:manager">PPSi0058.xml</policySetReference>
    <policySetReference ref="urn:mtas:PPS:i0058:employee">PPSi0058.xml</policySetReference>
    <policySetReference ref="urn:mtas:RPS:i0058:employee">RPSi0058.xml</policySetReference>
    
    <policySetReference ref="urn:mtas:RPS:i0059">RPSi0059.xml</policySetReference>
    <policySetReference ref="urn:mtas:PPS:i0059:manager">PPSi0059.xml</policySetReference>
    <policySetReference ref="urn:mtas:PPS:i0059:employee">PPSi0059.xml</policySetReference>
    <policySetReference ref="urn:mtas:RPS:i0059:employee">RPSi0059.xml</policySetReference>
    
    <policySetReference ref="urn:mtas:RPS:i0060">RPSi0060.xml</policySetReference>
    <policySetReference ref="urn:mtas:PPS:i0060:manager">PPSi0060.xml</policySetReference>
    <policySetReference ref="urn:mtas:PPS:i0060:employee">PPSi0060.xml</policySetReference>
    <policySetReference ref="urn:mtas:RPS:i0060:employee">RPSi0060.xml</policySetReference>
    
    <policySetReference ref="urn:mtas:RPS:i0061">RPSi0061.xml</policySetReference>
    <policySetReference ref="urn:mtas:PPS:i0061:manager">PPSi0061.xml</policySetReference>
    <policySetReference ref="urn:mtas:PPS:i0061:employee">PPSi0061.xml</policySetReference>
    <policySetReference ref="urn:mtas:RPS:i0061:employee">RPSi0061.xml</policySetReference>
    
    <policySetReference ref="urn:mtas:RPS:i0062">RPSi0062.xml</policySetReference>
    <policySetReference ref="urn:mtas:PPS:i0062:manager">PPSi0062.xml</policySetReference>
    <policySetReference ref="urn:mtas:PPS:i0062:employee">PPSi0062.xml</policySetReference>
    <policySetReference ref="urn:mtas:RPS:i0062:employee">RPSi0062.xml</policySetReference>
    
    <policySetReference ref="urn:mtas:RPS:i0063">RPSi0063.xml</policySetReference>
    <policySetReference ref="urn:mtas:PPS:i0063:manager">PPSi0063.xml</policySetReference>
    <policySetReference ref="urn:mtas:PPS:i0063:employee">PPSi0063.xml</policySetReference>
    <policySetReference ref="urn:mtas:RPS:i0063:employee">RPSi0063.xml</policySetReference>
    
    <policySetReference ref="urn:mtas:RPS:i0064">RPSi0064.xml</policySetReference>
    <policySetReference ref="urn:mtas:PPS:i0064:manager">PPSi0064.xml</policySetReference>
    <policySetReference ref="urn:mtas:PPS:i0064:employee">PPSi0064.xml</policySetReference>
    <policySetReference ref="urn:mtas:RPS:i0064:employee">RPSi0064.xml</policySetReference>
    
    <policySetReference ref="urn:mtas:RPS:i0065">RPSi0065.xml</policySetReference>
    <policySetReference ref="urn:mtas:PPS:i0065:manager">PPSi0065.xml</policySetReference>
    <policySetReference ref="urn:mtas:PPS:i0065:employee">PPSi0065.xml</policySetReference>
    <policySetReference ref="urn:mtas:RPS:i0065:employee">RPSi0065.xml</policySetReference>
    
    <policySetReference ref="urn:mtas:RPS:i0066">RPSi0066.xml</policySetReference>
    <policySetReference ref="urn:mtas:PPS:i0066:manager">PPSi0066.xml</policySetReference>
    <policySetReference ref="urn:mtas:PPS:i0066:employee">PPSi0066.xml</policySetReference>
    <policySetReference ref="urn:mtas:RPS:i0066:employee">RPSi0066.xml</policySetReference>
    
    <policySetReference ref="urn:mtas:RPS:i0067">RPSi0067.xml</policySetReference>
    <policySetReference ref="urn:mtas:PPS:i0067:manager">PPSi0067.xml</policySetReference>
    <policySetReference ref="urn:mtas:PPS:i0067:employee">PPSi0067.xml</policySetReference>
    <policySetReference ref="urn:mtas:RPS:i0067:employee">RPSi0067.xml</policySetReference>
    
    <policySetReference ref="urn:mtas:RPS:i0068">RPSi0068.xml</policySetReference>
    <policySetReference ref="urn:mtas:PPS:i0068:manager">PPSi0068.xml</policySetReference>
    <policySetReference ref="urn:mtas:PPS:i0068:employee">PPSi0068.xml</policySetReference>
    <policySetReference ref="urn:mtas:RPS:i0068:employee">RPSi0068.xml</policySetReference>
    
    <policySetReference ref="urn:mtas:RPS:i0069">RPSi0069.xml</policySetReference>
    <policySetReference ref="urn:mtas:PPS:i0069:manager">PPSi0069.xml</policySetReference>
    <policySetReference ref="urn:mtas:PPS:i0069:employee">PPSi0069.xml</policySetReference>
    <policySetReference ref="urn:mtas:RPS:i0069:employee">RPSi0069.xml</policySetReference>
    
    <policySetReference ref="urn:mtas:RPS:i0070">RPSi0070.xml</policySetReference>
    <policySetReference ref="urn:mtas:PPS:i0070:manager">PPSi0070.xml</policySetReference>
    <policySetReference ref="urn:mtas:PPS:i0070:employee">PPSi0070.xml</policySetReference>
    <policySetReference ref="urn:mtas:RPS:i0070:employee">RPSi0070.xml</policySetReference>
    
    <policySetReference ref="urn:mtas:RPS:i0071">RPSi0071.xml</policySetReference>
    <policySetReference ref="urn:mtas:PPS:i0071:manager">PPSi0071.xml</policySetReference>
    <policySetReference ref="urn:mtas:PPS:i0071:employee">PPSi0071.xml</policySetReference>
    <policySetReference ref="urn:mtas:RPS:i0071:employee">RPSi0071.xml</policySetReference>
    
    <policySetReference ref="urn:mtas:RPS:i0072">RPSi0072.xml</policySetReference>
    <policySetReference ref="urn:mtas:PPS:i0072:manager">PPSi0072.xml</policySetReference>
    <policySetReference ref="urn:mtas:PPS:i0072:employee">PPSi0072.xml</policySetReference>
    <policySetReference ref="urn:mtas:RPS:i0072:employee">RPSi0072.xml</policySetReference>
    
    <policySetReference ref="urn:mtas:RPS:i0073">RPSi0073.xml</policySetReference>
    <policySetReference ref="urn:mtas:PPS:i0073:manager">PPSi0073.xml</policySetReference>
    <policySetReference ref="urn:mtas:PPS:i0073:employee">PPSi0073.xml</policySetReference>
    <policySetReference ref="urn:mtas:RPS:i0073:employee">RPSi0073.xml</policySetReference>
    
    <policySetReference ref="urn:mtas:RPS:i0074">RPSi0074.xml</policySetReference>
    <policySetReference ref="urn:mtas:PPS:i0074:manager">PPSi0074.xml</policySetReference>
    <policySetReference ref="urn:mtas:PPS:i0074:employee">PPSi0074.xml</policySetReference>
    <policySetReference ref="urn:mtas:RPS:i0074:employee">RPSi0074.xml</policySetReference>
    
    <policySetReference ref="urn:mtas:RPS:i0075">RPSi0075.xml</policySetReference>
    <policySetReference ref="urn:mtas:PPS:i0075:manager">PPSi0075.xml</policySetReference>
    <policySetReference ref="urn:mtas:PPS:i0075:employee">PPSi0075.xml</policySetReference>
    <policySetReference ref="urn:mtas:RPS:i0075:employee">RPSi0075.xml</policySetReference>
    
    <policySetReference ref="urn:mtas:RPS:i0076">RPSi0076.xml</policySetReference>
    <policySetReference ref="urn:mtas:PPS:i0076:manager">PPSi0076.xml</policySetReference>
    <policySetReference ref="urn:mtas:PPS:i0076:employee">PPSi0076.xml</policySetReference>
    <policySetReference ref="urn:mtas:RPS:i0076:employee">RPSi0076.xml</policySetReference>
    
    <policySetReference ref="urn:mtas:RPS:i0077">RPSi0077.xml</policySetReference>
    <policySetReference ref="urn:mtas:PPS:i0077:manager">PPSi0077.xml</policySetReference>
    <policySetReference ref="urn:mtas:PPS:i0077:employee">PPSi0077.xml</policySetReference>
    <policySetReference ref="urn:mtas:RPS:i0077:employee">RPSi0077.xml</policySetReference>
    
    <policySetReference ref="urn:mtas:RPS:i0078">RPSi0078.xml</policySetReference>
    <policySetReference ref="urn:mtas:PPS:i0078:manager">PPSi0078.xml</policySetReference>
    <policySetReference ref="urn:mtas:PPS:i0078:employee">PPSi0078.xml</policySetReference>
    <policySetReference ref="urn:mtas:RPS:i0078:employee">RPSi0078.xml</policySetReference>
    
    <policySetReference ref="urn:mtas:RPS:i0079">RPSi0079.xml</policySetReference>
    <policySetReference ref="urn:mtas:PPS:i0079:manager">PPSi0079.xml</policySetReference>
    <policySetReference ref="urn:mtas:PPS:i0079:employee">PPSi0079.xml</policySetReference>
    <policySetReference ref="urn:mtas:RPS:i0079:employee">RPSi0079.xml</policySetReference>
    
    <policySetReference ref="urn:mtas:RPS:i0080">RPSi0080.xml</policySetReference>
    <policySetReference ref="urn:mtas:PPS:i0080:manager">PPSi0080.xml</policySetReference>
    <policySetReference ref="urn:mtas:PPS:i0080:employee">PPSi0080.xml</policySetReference>
    <policySetReference ref="urn:mtas:RPS:i0080:employee">RPSi0080.xml</policySetReference>
    
    <policySetReference ref="urn:mtas:RPS:i0081">RPSi0081.xml</policySetReference>
    <policySetReference ref="urn:mtas:PPS:i0081:manager">PPSi0081.xml</policySetReference>
    <policySetReference ref="urn:mtas:PPS:i0081:employee">PPSi0081.xml</policySetReference>
    <policySetReference ref="urn:mtas:RPS:i0081:employee">RPSi0081.xml</policySetReference>
    
    <policySetReference ref="urn:mtas:RPS:i0082">RPSi0082.xml</policySetReference>
    <policySetReference ref="urn:mtas:PPS:i0082:manager">PPSi0082.xml</policySetReference>
    <policySetReference ref="urn:mtas:PPS:i0082:employee">PPSi0082.xml</policySetReference>
    <policySetReference ref="urn:mtas:RPS:i0082:employee">RPSi0082.xml</policySetReference>
    
    <policySetReference ref="urn:mtas:RPS:i0083">RPSi0083.xml</policySetReference>
    <policySetReference ref="urn:mtas:PPS:i0083:manager">PPSi0083.xml</policySetReference>
    <policySetReference ref="urn:mtas:PPS:i0083:employee">PPSi0083.xml</policySetReference>
    <policySetReference ref="urn:mtas:RPS:i0083:employee">RPSi0083.xml</policySetReference>
    
    <policySetReference ref="urn:mtas:RPS:i0084">RPSi0084.xml</policySetReference>
    <policySetReference ref="urn:mtas:PPS:i0084:manager">PPSi0084.xml</policySetReference>
    <policySetReference ref="urn:mtas:PPS:i0084:employee">PPSi0084.xml</policySetReference>
    <policySetReference ref="urn:mtas:RPS:i0084:employee">RPSi0084.xml</policySetReference>
    
    <policySetReference ref="urn:mtas:RPS:i0085">RPSi0085.xml</policySetReference>
    <policySetReference ref="urn:mtas:PPS:i0085:manager">PPSi0085.xml</policySetReference>
    <policySetReference ref="urn:mtas:PPS:i0085:employee">PPSi0085.xml</policySetReference>
    <policySetReference ref="urn:mtas:RPS:i0085:employee">RPSi0085.xml</policySetReference>
    
    <policySetReference ref="urn:mtas:RPS:i0086">RPSi0086.xml</policySetReference>
    <policySetReference ref="urn:mtas:PPS:i0086:manager">PPSi0086.xml</policySetReference>
    <policySetReference ref="urn:mtas:PPS:i0086:employee">PPSi0086.xml</policySetReference>
    <policySetReference ref="urn:mtas:RPS:i0086:employee">RPSi0086.xml</policySetReference>
    
    <policySetReference ref="urn:mtas:RPS:i0087">RPSi0087.xml</policySetReference>
    <policySetReference ref="urn:mtas:PPS:i0087:manager">PPSi0087.xml</policySetReference>
    <policySetReference ref="urn:mtas:PPS:i0087:employee">PPSi0087.xml</policySetReference>
    <policySetReference ref="urn:mtas:RPS:i0087:employee">RPSi0087.xml</policySetReference>
    
    <policySetReference ref="urn:mtas:RPS:i0088">RPSi0088.xml</policySetReference>
    <policySetReference ref="urn:mtas:PPS:i0088:manager">PPSi0088.xml</policySetReference>
    <policySetReference ref="urn:mtas:PPS:i0088:employee">PPSi0088.xml</policySetReference>
    <policySetReference ref="urn:mtas:RPS:i0088:employee">RPSi0088.xml</policySetReference>
    
    <policySetReference ref="urn:mtas:RPS:i0089">RPSi0089.xml</policySetReference>
    <policySetReference ref="urn:mtas:PPS:i0089:manager">PPSi0089.xml</policySetReference>
    <policySetReference ref="urn:mtas:PPS:i0089:employee">PPSi0089.xml</policySetReference>
    <policySetReference ref="urn:mtas:RPS:i0089:employee">RPSi0089.xml</policySetReference>
    
    <policySetReference ref="urn:mtas:RPS:i0090">RPSi0090.xml</policySetReference>
    <policySetReference ref="urn:mtas:PPS:i0090:manager">PPSi0090.xml</policySetReference>
    <policySetReference ref="urn:mtas:PPS:i0090:employee">PPSi0090.xml</policySetReference>
    <policySetReference ref="urn:mtas:RPS:i0090:employee">RPSi0090.xml</policySetReference>
    
    <policySetReference ref="urn:mtas:RPS:i0091">RPSi0091.xml</policySetReference>
    <policySetReference ref="urn:mtas:PPS:i0091:manager">PPSi0091.xml</policySetReference>
    <policySetReference ref="urn:mtas:PPS:i0091:employee">PPSi0091.xml</policySetReference>
    <policySetReference ref="urn:mtas:RPS:i0091:employee">RPSi0091.xml</policySetReference>
    
    <policySetReference ref="urn:mtas:RPS:i0092">RPSi0092.xml</policySetReference>
    <policySetReference ref="urn:mtas:PPS:i0092:manager">PPSi0092.xml</policySetReference>
    <policySetReference ref="urn:mtas:PPS:i0092:employee">PPSi0092.xml</policySetReference>
    <policySetReference ref="urn:mtas:RPS:i0092:employee">RPSi0092.xml</policySetReference>
    
    <policySetReference ref="urn:mtas:RPS:i0093">RPSi0093.xml</policySetReference>
    <policySetReference ref="urn:mtas:PPS:i0093:manager">PPSi0093.xml</policySetReference>
    <policySetReference ref="urn:mtas:PPS:i0093:employee">PPSi0093.xml</policySetReference>
    <policySetReference ref="urn:mtas:RPS:i0093:employee">RPSi0093.xml</policySetReference>
    
    <policySetReference ref="urn:mtas:RPS:i0094">RPSi0094.xml</policySetReference>
    <policySetReference ref="urn:mtas:PPS:i0094:manager">PPSi0094.xml</policySetReference>
    <policySetReference ref="urn:mtas:PPS:i0094:employee">PPSi0094.xml</policySetReference>
    <policySetReference ref="urn:mtas:RPS:i0094:employee">RPSi0094.xml</policySetReference>
    
    <policySetReference ref="urn:mtas:RPS:i0095">RPSi0095.xml</policySetReference>
    <policySetReference ref="urn:mtas:PPS:i0095:manager">PPSi0095.xml</policySetReference>
    <policySetReference ref="urn:mtas:PPS:i0095:employee">PPSi0095.xml</policySetReference>
    <policySetReference ref="urn:mtas:RPS:i0095:employee">RPSi0095.xml</policySetReference>
    
    <policySetReference ref="urn:mtas:RPS:i0096">RPSi0096.xml</policySetReference>
    <policySetReference ref="urn:mtas:PPS:i0096:manager">PPSi0096.xml</policySetReference>
    <policySetReference ref="urn:mtas:PPS:i0096:employee">PPSi0096.xml</policySetReference>
    <policySetReference ref="urn:mtas:RPS:i0096:employee">RPSi0096.xml</policySetReference>
    
    <policySetReference ref="urn:mtas:RPS:i0097">RPSi0097.xml</policySetReference>
    <policySetReference ref="urn:mtas:PPS:i0097:manager">PPSi0097.xml</policySetReference>
    <policySetReference ref="urn:mtas:PPS:i0097:employee">PPSi0097.xml</policySetReference>
    <policySetReference ref="urn:mtas:RPS:i0097:employee">RPSi0097.xml</policySetReference>
    
    <policySetReference ref="urn:mtas:RPS:i0098">RPSi0098.xml</policySetReference>
    <policySetReference ref="urn:mtas:PPS:i0098:manager">PPSi0098.xml</policySetReference>
    <policySetReference ref="urn:mtas:PPS:i0098:employee">PPSi0098.xml</policySetReference>
    <policySetReference ref="urn:mtas:RPS:i0098:employee">RPSi0098.xml</policySetReference>
    
    <policySetReference ref="urn:mtas:RPS:i0099">RPSi0099.xml</policySetReference>
    <policySetReference ref="urn:mtas:PPS:i0099:manager">PPSi0099.xml</policySetReference>
    <policySetReference ref="urn:mtas:PPS:i0099:employee">PPSi0099.xml</policySetReference>
    <policySetReference ref="urn:mtas:RPS:i0099:employee">RPSi0099.xml</policySetReference>
    
</test>
